rimo_storage/__init__.py
rimo_storage/cache.py
rimo_storage-1.4.0.dist-info/METADATA
rimo_storage-1.4.0.dist-info/WHEEL
rimo_storage-1.4.0.dist-info/top_level.txt
rimo_storage-1.4.0.dist-info/RECORD
