Metadata-Version: 2.1
Name: rimo-storage
Version: 1.4.0
Summary: 好！
Home-page: https://github.com/RimoChan/rimo_storage
Author: RimoChan
Author-email: the@librian.net
Classifier: Programming Language :: Python :: 3
Classifier: Operating System :: OS Independent
Requires-Python: >=3.6
